[
  {
    "fromYear": 2017,
    "data": {
      "1.1": "Novo leto",
      "2.1": "Novo leto",
      "8.2": "Prešernov dan",
      "27.4": "Dan upora proti okupatorju",
      "EASTER": "Velikonočna nedelja",
      "EASTER_MONDAY": "Velikonočni ponedeljek",
      "1.5": "Praznik dela",
      "2.5": "Praznik dela",
      "25.6": "Dan državnosti",
      "15.8": "Marijino vnebovzetje",
      "31.10": "Dan reformacije",
      "1.11": "Dan spomina na mrtve",
      "25.12": "Božič",
      "26.12": "Dan samostojnosti in enotnosti"
    }
  }
]
